ovbpclient/__init__.py
ovbpclient/client.py
ovbpclient/exceptions.py
ovbpclient/json.py
ovbpclient/rest_client.py
ovbpclient/util.py
ovbpclient/version.py
ovbpclient/endpoints/__init__.py
ovbpclient/endpoints/base.py
ovbpclient/endpoints/series.py
ovbpclient/models/__init__.py
ovbpclient/models/base.py
ovbpclient/models/mixin_active.py
ovbpclient/models/odata/__init__.py
ovbpclient/models/odata/analysis.py
ovbpclient/models/odata/base_feeder.py
ovbpclient/models/odata/cleaner.py
ovbpclient/models/odata/ftp_account.py
ovbpclient/models/odata/ftp_entry.py
ovbpclient/models/odata/gate.py
ovbpclient/models/odata/gate_ftp_account.py
ovbpclient/models/odata/importer.py
ovbpclient/models/odata/mixin_generator.py
ovbpclient/models/odata/project.py
ovbpclient/models/odata/series.py
ovbpclient/models/odata/task.py
ovbpclient/models/oteams/__init__.py
ovbpclient/models/oteams/organization.py
ovbpclient/models/oteams/project.py
ovbpclient/models/oteams/user.py
ovbpclient/resources/multiclean_config_model.xlsx
ovbpclient/tools/__init__.py
ovbpclient/tools/clear.py
ovbpclient/tools/deactivate.py
ovbpclient/tools/delete.py
ovbpclient/tools/download.py
tests/__init__.py
tests/test_main.py
ovbpclient-1.5.2.dist-info/LICENSE.txt
ovbpclient-1.5.2.dist-info/METADATA
ovbpclient-1.5.2.dist-info/WHEEL
ovbpclient-1.5.2.dist-info/top_level.txt
ovbpclient-1.5.2.dist-info/RECORD
