Metadata-Version: 2.1
Name: ovbpclient
Version: 1.5.2
Home-page: https://github.com/openergy/ovbpclient
Author: Openergy team
Author-email: contact@openergy.fr
Classifier: Programming Language :: Python
Classifier: Development Status :: 5 - Production/Stable
Classifier: Intended Audience :: Science/Research
Classifier: Natural Language :: French
Classifier: Operating System :: POSIX :: Linux
Classifier: Programming Language :: Python :: 3.6
Classifier: Programming Language :: Python :: 3.7
Classifier: Programming Language :: Python :: 3.8
Classifier: Programming Language :: Python :: 3.9
Classifier: Programming Language :: Python :: 3.1
Classifier: Topic :: Scientific/Engineering :: Physics
License-File: LICENSE.txt
Requires-Dist: requests (<3.0,>=2.23.0)
Requires-Dist: openpyxl (<4.0,>=2.0)
Requires-Dist: pandas (<2.0,>=0.0)
Requires-Dist: ftputil (<4.0,>=3.4)
Requires-Dist: python-slugify (<6.0,>=3.0.2)
